kumade/__init__.py
kumade/builder.py
kumade/cli.py
kumade/config.py
kumade/decorator.py
kumade/loader.py
kumade/manager.py
kumade/py.typed
kumade/runner.py
kumade/task.py
kumade/utility.py
kumade/concurrent/__init__.py
kumade/concurrent/printer.py
kumade/concurrent/runner.py
kumade-0.3.0.dist-info/LICENSE
kumade-0.3.0.dist-info/METADATA
kumade-0.3.0.dist-info/WHEEL
kumade-0.3.0.dist-info/entry_points.txt
kumade-0.3.0.dist-info/top_level.txt
kumade-0.3.0.dist-info/RECORD
