Metadata-Version: 2.1
Name: kumade
Version: 0.3.0
Summary: A make-like build utility for Python.
Author-email: yamaimo <hello@yamaimo.dev>
License: MIT License
Project-URL: Homepage, https://github.com/yamaimo/kumade
License-File: LICENSE
Provides-Extra: develop
Requires-Dist: pysen ; extra == 'develop'
Requires-Dist: black ; extra == 'develop'
Requires-Dist: flake8 ; extra == 'develop'
Requires-Dist: isort ; extra == 'develop'
Requires-Dist: mypy ; extra == 'develop'
Requires-Dist: coverage ; extra == 'develop'
Requires-Dist: build ; extra == 'develop'
Requires-Dist: twine ; extra == 'develop'
Requires-Dist: types-docutils ; extra == 'develop'
